{
 "based_on": "creation",
 "chart_name": "customer crea",
 "chart_type": "Sum",
 "creation": "2023-04-20 13:00:06.709304",
 "docstatus": 0,
 "doctype": "Dashboard Chart",
 "document_type": "Customer",
 "dynamic_filters_json": "[]",
 "filters_json": "[]",
 "group_by_type": "Count",
 "idx": 0,
 "is_public": 0,
 "is_standard": 1,
 "modified": "2023-04-20 13:03:22.710296",
 "modified_by": "Administrator",
 "module": "oxo",
 "name": "customer crea",
 "number_of_groups": 0,
 "owner": "Administrator",
 "parent_document_type": "",
 "roles": [],
 "source": "",
 "time_interval": "Yearly",
 "timeseries": 1,
 "timespan": "Last Month",
 "type": "Line",
 "use_report_chart": 0,
 "value_based_on": "",
 "y_axis": []
}